README.md
vibesql-0.1.3.dist-info/METADATA
vibesql-0.1.3.dist-info/WHEEL
vibesql/__init__.py
vibesql/__init__.pyi
vibesql/py.typed
vibesql/vibesql.abi3.so
vibesql-0.1.3.dist-info/RECORD
